pyplatform/udf/__init__.py
pyplatform/udf/udf.py
pyplatform_udf-0.0.4.dist-info/METADATA
pyplatform_udf-0.0.4.dist-info/WHEEL
pyplatform_udf-0.0.4.dist-info/top_level.txt
pyplatform_udf-0.0.4.dist-info/RECORD
